falconlib/conftest.py
falconlib/falconlib.py
falconlib/x__init__.py
falconlib/tests/gendoc.py
falconlib/tests/test_010_lib.py
falconlib-0.0.14.dist-info/LICENSE
falconlib-0.0.14.dist-info/METADATA
falconlib-0.0.14.dist-info/WHEEL
falconlib-0.0.14.dist-info/top_level.txt
falconlib-0.0.14.dist-info/RECORD
