Metadata-Version: 2.1
Name: falconlib
Version: 0.0.14
Summary: Client-side library for accessing the falconapi restful service.
Author-email: "Thomas J. Daley, Esq." <tjd@powerdaley.com>
License: BSD 2-Clause License
Project-URL: Homepage, https://github.com/tjdaley/falconlib
Project-URL: Bug Tracker, https://github.com/tjdaley/falconlib/issues
Keywords: falconapi,falconlib
Classifier: Programming Language :: Python :: 3
Classifier: License :: OSI Approved :: BSD License
Classifier: Operating System :: OS Independent
Classifier: Development Status :: 1 - Planning
Classifier: Intended Audience :: Developers
Classifier: Natural Language :: English
Classifier: Topic :: Software Development :: Libraries :: Python Modules
Requires-Python: >3.9
License-File: LICENSE
Requires-Dist: requests
